AUTHORS.rst
CONTRIBUTING.rst
LICENSE
MANIFEST.in
README.rst
requirements.txt
setup.cfg
setup.py
versioneer.py
crystalmapping/__init__.py
crystalmapping/_vend.py
crystalmapping/_version.py
crystalmapping/baseobject.py
crystalmapping/callbacks.py
crystalmapping/crystalmapper.py
crystalmapping/datafiles.py
crystalmapping/peakindexer.py
crystalmapping/plans.py
crystalmapping/preprocessor.py
crystalmapping/servers.py
crystalmapping/sim.py
crystalmapping/simulations.py
crystalmapping/ubmatrix.py
crystalmapping.egg-info/PKG-INFO
crystalmapping.egg-info/SOURCES.txt
crystalmapping.egg-info/dependency_links.txt
crystalmapping.egg-info/entry_points.txt
crystalmapping.egg-info/top_level.txt
crystalmapping/data/CG_0046_full_range_grid_scan_0_degree_40_p_20_w.nc
crystalmapping/data/CG_0046_full_range_grid_scan_90_degree_40_p_20_w.nc
crystalmapping/data/CeO2_0.25x0.25_beam.poni
crystalmapping/data/Ni.cif
crystalmapping/data/Ni.poni
crystalmapping/data/image.png
crystalmapping/data/tio2_rutile.cif
crystalmapping/tests/__init__.py
crystalmapping/tests/conftest.py
crystalmapping/tests/test_callbacks.py
crystalmapping/tests/test_crystal_mapping.py
crystalmapping/tests/test_peak_indexing.py
crystalmapping/tests/test_plans.py
crystalmapping/tests/test_preprocessor.py
crystalmapping/tests/test_ubmatrix.py