Metadata-Version: 2.1
Name: crystalmapping
Version: 0.2.0
Summary: A python package to do crystal mapping.
Home-page: https://github.com/st3107/crystalmapping
Author: Songsheng Tao
Author-email: st3107@columbia.edu
License: BSD (3-clause)
Platform: UNKNOWN
Classifier: Development Status :: 2 - Pre-Alpha
Classifier: Natural Language :: English
Classifier: Programming Language :: Python :: 3
Requires-Python: >=3.6
License-File: LICENSE
License-File: AUTHORS.rst
